<?xml version="1.0" encoding="UTF-8"?>
<Template schemaLocation="http://morfeo-project.org/2007/Template">

<!-- Informacion relativa al gadget -->

<Catalog.ResourceDescription>

	<Vendor>Morfeo</Vendor>

	<Name>Frase Del Dia</Name>

	<Version>1.0</Version>

	<Author>AlbertoChavesJiménez</Author>

	<Mail>achaves@pegaso.ls.fi.upm.es</Mail>

	<Description>Muestra la frase del dia</Description>

	<ImageURI>http://demo.ezweb.morfeo-project.org/repository/fraseDelDia/images/fraseDelDia.png</ImageURI>

	<WikiURI>http://hola.com</WikiURI>

</Catalog.ResourceDescription>
 	           
<!-- Preferencias -->

<Platform.Preferences>
	<!-- El usuario puede seleccionar la URL de la frase -->
	<!--<Preference name="url" type="text" description="Descripción" label="Fuente de la frase" default="http://frasedeldia.net/feed/"/>-->

	<Preference name="url" type="list" description="Descripción" label="Fuente de la frase" default="1">
		<Option value="1" name="Frasedeldia.net"/>
		<Option value="2" name="Proverbia.net"/>
	</Preference>

</Platform.Preferences>


<!-- Propiedades persistentes -->

<Platform.StateProperties>

</Platform.StateProperties>

<!-- Wiring -->


<Plataform.Wiring>

</Plataform.Wiring>

 
<!-- Link al codigo -->
<Platform.Link>

	<XHTML href="http://demo.ezweb.morfeo-project.org/repository/fraseDelDia/fraseDelDia.html"/>

</Platform.Link>

<!-- Tamaño incial del gadget -->
<Platform.Rendering width="6" height="24"/>

 
<!-- Variables de contexto -->

<Platform.Context>
</Platform.Context>

</Template>
